japronto/reloader.py
japronto/__main__.py
japronto/cpu_features.c
japronto/__init__.py
japronto/runner.py
japronto/capsule.c
japronto/router/test_route.py
japronto/router/matcher.py
japronto/router/test_matcher.py
japronto/router/__init__.py
japronto/router/cmatcher.cpython-36m-x86_64-linux-gnu.so
japronto/router/match_dict.c
japronto/router/analyzer.py
japronto/router/cmatcher_ext.py
japronto/router/cmatcher.c
japronto/router/route.py
japronto/router/test_analyzer.py
japronto/response/cresponse.c
japronto/response/py.py
japronto/response/cresponse.cpython-36m-x86_64-linux-gnu.so
japronto/response/__init__.py
japronto/response/cresponse_ext.py
japronto/parser/cffiparser.py
japronto/parser/test_parser.py
japronto/parser/__init__.py
japronto/parser/cparser.c
japronto/parser/build_libpicohttpparser.py
japronto/parser/cparser_ext.py
japronto/app/__init__.py
japronto/request/__init__.py
japronto/request/crequest.cpython-36m-x86_64-linux-gnu.so
japronto/request/crequest.c
japronto/request/crequest_ext.py
japronto/protocol/cprotocol_ext.py
japronto/protocol/null.py
japronto/protocol/__init__.py
japronto/protocol/handler.py
japronto/protocol/cprotocol.cpython-36m-x86_64-linux-gnu.so
japronto/protocol/creaper.c
japronto/protocol/creaper.cpython-36m-x86_64-linux-gnu.so
japronto/protocol/creaper_ext.py
japronto/protocol/cprotocol.c
japronto/protocol/tracing.py
japronto/protocol/generator_ext.py
japronto/pipeline/test_pipeline.py
japronto/pipeline/__init__.py
japronto/pipeline/cpipeline.c
japronto/pipeline/cpipeline_ext.py
japronto-0.1.2.dist-info/WHEEL
japronto-0.1.2.dist-info/top_level.txt
japronto-0.1.2.dist-info/METADATA
japronto-0.1.2.dist-info/RECORD
japronto-0.1.2.dist-info/entry_points.txt
